rdsdriver/__init__.py
rdsdriver/dm/__init__.py
rdsdriver/dm/dm.py
rdsdriver/dm/dmPython.cpython-36-aarch64-linux-gnu.so
rdsdriver/dm/dmPython.cpython-36-x86_64-linux-gnu.so
rdsdriver/dm/dmPython.cpython-38-aarch64-linux-gnu.so
rdsdriver/dm/dmPython.cpython-38-x86_64-linux-gnu.so
rdsdriver/mysql/__init__.py
rdsdriver/mysql/mysql.py
RDSDriver-1.3.3.dist-info/METADATA
RDSDriver-1.3.3.dist-info/WHEEL
RDSDriver-1.3.3.dist-info/top_level.txt
RDSDriver-1.3.3.dist-info/RECORD
