Metadata-Version: 2.1
Name: RDSDriver
Version: 1.3.3
Summary: RDS DB API 2.0 driver.
License: MIT License
Project-URL: Source Code, https://devops.aishu.cn:22/AISHUDevOps/KWeaver/_git/kw-proton-rds
Platform: any
Requires-Python: >=3.0, <4
Requires-Dist: pymysql
